<!DOCTYPE suite SYSTEM "https://testng.org/testng-1.0.dtd" >
<suite name="Classları calıstırma" parallel="classes" thread-count="2">

    <test name="Istenen class'ları calıstırma">

        <classes>
            <class name="tests.day15_softAssert.C01_SoftAssert"></class>
            <class name="tests.day16_SmokeTests.C03_SwitchingWindows"></class>
            <class name="tests.day14_testNGFramework.C03_NutellaTesti"></class>
            <class name="tests.day15_softAssert.C03_PozitifLoginTesti"></class>
        </classes>
    </test>

</suite>